modalic/__init__.py
modalic/_version.py
modalic/run.py
modalic/api/__init__.py
modalic/api/common/__init__.py
modalic/api/common/client.py
modalic/api/common/communication.py
modalic/api/common/trainer.py
modalic/api/common/proto/__init__.py
modalic/api/common/proto/mosaic_pb2.py
modalic/api/common/proto/mosaic_pb2_grpc.py
modalic/api/tf/__init__.py
modalic/api/tf/tf_client.py
modalic/api/tf/tf_func.py
modalic/api/tf/tf_utils.py
modalic/api/torch/__init__.py
modalic/api/torch/pytorch_client.py
modalic/api/torch/torch_func.py
modalic/api/torch/torch_utils.py
modalic/bin/aggregator
modalic/client/__init__.py
modalic/client/client.py
modalic/client/decor.py
modalic/client/internal_client.py
modalic/client/mosaic_python_sdk.cpython-38-darwin.so
modalic/config/__init__.py
modalic/config/config.py
modalic/data/__init__.py
modalic/data/data.py
modalic/data/misc.py
modalic/logging/__init__.py
modalic/logging/logging.py
modalic/logging/monitor.py
modalic/platforms/__init__.py
modalic/platforms/common/__init__.py
modalic/platforms/common/serde.py
modalic/platforms/tf/__init__.py
modalic/platforms/tf/keras_utils.py
modalic/platforms/torch/__init__.py
modalic/platforms/torch/misc.py
modalic/server/__init__.py
modalic/server/api.py
modalic/server/server.py
modalic/simulation/__init__.py
modalic/simulation/pool.py
modalic/simulation/scheduler.py
modalic/storage/__init__.py
modalic/storage/store.py
modalic/utils/__init__.py
modalic/utils/convert.py
modalic/utils/misc.py
modalic/utils/protocol.py
modalic/utils/serde.py
modalic/utils/shared.py
modalic-0.2.0.dist-info/LICENSE
modalic-0.2.0.dist-info/METADATA
modalic-0.2.0.dist-info/WHEEL
modalic-0.2.0.dist-info/top_level.txt
modalic-0.2.0.dist-info/RECORD
