Metadata-Version: 2.1
Name: modalic
Version: 0.2.0
Summary: "Python SDK library for using the Modalic Federated Learning Operations Platform."
License: "Apache-2.0"
Keywords: "Python","Federated Learning","Machine Learning","SDK","MLOps"
Classifier: Development Status :: 3 - Alpha
Classifier: Intended Audience :: Developers
Classifier: Intended Audience :: Science/Research
Classifier: License :: OSI Approved :: Apache Software License
Classifier: Programming Language :: Python :: 3
Classifier: Programming Language :: Python :: 3.8
Classifier: Programming Language :: Python :: 3.9
Classifier: Programming Language :: Python :: 3.10
Classifier: Operating System :: POSIX
Classifier: Operating System :: MacOS :: MacOS X
Classifier: Operating System :: Microsoft :: Windows
Classifier: Topic :: System :: Distributed Computing
Classifier: Topic :: Scientific/Engineering :: Artificial Intelligence
Classifier: Topic :: Software Development :: Libraries :: Python Modules
Requires-Python: >=3.8
License-File: LICENSE
Requires-Dist: numpy (>=1.23.0)
Requires-Dist: grpcio (>=1.43.0)
Requires-Dist: grpcio-tools (>=1.43.0)
Requires-Dist: protobuf (==3.20)
Requires-Dist: toml (>=0.10.2)
Requires-Dist: backoff (>=2.2.1)
